{
  "articles": [
    {
      "slug": "ias-district-magistrate",
      "title": "A Day in the Life of an IAS Officer — What Does a District Magistrate Actually Do?",
      "description": "Discover what a typical day looks like for an IAS officer serving as a District Magistrate in India's most powerful administrative post.",
      "category": "UPSC",
      "icon": "👔",
      "readTime": "12 min read",
      "content": "When people think about the most powerful job in India, they often imagine the Prime Minister or Chief Justice. But at the district level, there's one person who holds enormous power: the District Magistrate, an IAS officer.\n\n**6:00 AM — The Morning Begins**\n\nThe alarm goes off in the sprawling government bungalow — a magnificent Victorian-era mansion with high ceilings, manicured lawns, and a compound that's bigger than most schools. This isn't an office; it's the DM's residence. For many IAS officers, the home and workplace blur together.\n\nThe DM goes for a 45-minute walk through the compound gardens, sometimes with the security detail following at a distance. The gardener has already arranged fresh flowers in the living room. The cook is preparing breakfast — usually a mix of Indian and continental options.\n\n**8:30 AM — Reading Files**\n\nBefore heading to office, the DM spends an hour reading the previous night's files. In the file room, a peon has organized everything in order of priority: pending court cases, law & order updates, development projects, and citizen complaints.\n\nAs DM, this officer has powers that rival a 19th-century British administrator. They can:\n- Order arrests for civil disobedience\n- Approve budgets worth thousands of crores\n- Declare public holidays\n- Commandeer buildings for emergencies\n- Grant land licenses\n- Supervise elections\n\n**10:00 AM — Staff Briefing**\n\nAt the district headquarters, dozens of officers await. The DM sits at the head of a long wooden table. There's an unspoken hierarchy: when the DM enters, everyone rises.\n\nToday's agenda includes:\n- A murder case that requires intervention\n- Preparations for a visit by a national leader\n- Drought relief measures for villages in the district\n- A school building collapse that needs investigation\n\nThe DM delegates, decides, and dictates policy. One word can set hundreds of people in motion.\n\n**11:30 AM — Field Visit**\n\nThe official motorcade — usually 3-4 vehicles with security personnel — heads to a village 40 km away. The DM is inspecting a government scheme that's supposed to build water tanks for drought-hit areas.\n\nBut when they arrive, villagers complain that the contractor has abandoned the work halfway. The DM's security team immediately begins taking photographs. Within hours, action will be taken against the contractor.\n\nThis is the reality of governance. The DM can order arrests, demand explanations, and ensure accountability with a single phone call.\n\n**1:00 PM — Lunch**\n\nBack at the government bungalow, lunch is served in the dining hall. The spread includes both traditional cuisine and Western dishes. The DM sometimes eats alone, sometimes with visiting officials or family.\n\nThe bill? Zero rupees. It's all part of the officer's perks.\n\n**2:30 PM — Public Grievance Hearing (Jan Sunwai)**\n\nThis is the part that reminds us that democracy still works at the grassroots level. For two hours, the DM sits in an open office where any citizen can present their grievance.\n\nToday, a farmer complains about land dispute. An elderly woman seeks a pension. A shopkeeper wants permission to open a food court. A student wants admission to a government school.\n\nThe DM listens, makes notes, and assigns officers to resolve each case. There's no waiting period, no application forms in triplicate. Just direct access to power.\n\n**4:00 PM — VIP Visit**\n\nA senior politician is visiting the district. The DM must brief them on current issues, arrange security, and ensure everything runs smoothly. In India's political system, an IAS officer must balance between being technically neutral and practically political.\n\n**5:30 PM — Administrative Decisions**\n\nBack at the office, the DM reviews proposals:\n- A new road project costing ₹50 crores\n- Recommendations for police transfers\n- Applications for disaster relief\n- Promotion recommendations\n\nEach decision will affect thousands of lives. The weight of this responsibility is something no exam can prepare you for.\n\n**7:00 PM — Officer's Club**\n\nThe evening is spent at the district's elite Officer's Club, where IAS, IPS, forest officers, and other senior bureaucrats gather. It's a place where relationships are built, gossip is exchanged, and alliances are formed.\n\nThe DM is the de facto leader here, often picking up the bill (from their generous entertainment allowance).\n\n**The Perks Are Real**\n\n- **Housing**: A 5-bedroom bungalow worth ₹1+ crore, maintained by government staff\n- **Transport**: An official car with driver, fuel, and maintenance\n- **Staff**: Personal cook, gardener, sweeper, security personnel\n- **Medical**: Free treatment at government hospitals, plus coverage for family\n- **Children's Education**: Reserved seats in elite schools\n- **Entertainment Allowance**: ₹5,000+ monthly for official events\n- **Pension**: A secure pension after 20 years of service\n- **Respect**: An officer commands instant respect in society\n\n**The Salary Breakdown**\n\n- Base Pay (Level 10): ₹56,100\n- Dearness Allowance (50%): ₹28,050\n- HRA (30% for metro): ₹16,830\n- Transport Allowance: ₹3,600\n- Total Monthly Gross: ₹1,04,580\n- After deductions (NPS, tax): Around ₹70,000-80,000 in-hand\n\nBut the true value? Consider that food, housing, and utilities are essentially free. The true earning power is 2-3x the salary.\n\n**The Weight of Responsibility**\n\nFor all the glamour and power, an IAS officer carries enormous responsibility. During natural disasters, communal violence, or political crises, the DM must ensure law and order, protect citizens, and maintain normalcy.\n\nSleep-deprived nights during elections, riots during communal tensions, and endless paperwork are realities. The power is real, but so are the challenges.\n\n**Why This Matters**\n\nThe IAS is India's most powerful administrative service. If you're considering government service, remember that the power and prestige come with the expectation to serve 1.4 billion people. That's both the challenge and the calling.\n\nFor aspirants: The IAS isn't just about salary. It's about wielding legitimate power to improve lives. If that excites you, this is your path."
    },
    {
      "slug": "sbi-po-bank-manager",
      "title": "A Day in the Life of an SBI PO — From Trainee to Branch Manager",
      "description": "Follow an SBI PO through their journey from trainee to branch manager — handling crores, approving loans, and leading a bank team.",
      "category": "Banking",
      "icon": "🏦",
      "readTime": "11 min read",
      "content": "The alarm rings at 6:30 AM in a comfortable apartment, courtesy of SBI's housing loan at just 1% interest. Meet Arjun, an SBI PO (Probationary Officer) who's now a Branch Manager at one of Mumbai's busiest branches, overseeing ₹400 crores in assets.\n\n**6:30 AM — Morning Routine**\n\nUnlike the IAS officer with a bungalow, Arjun lives in a modern apartment. The mortgage is affordable thanks to SBI's generous housing loan scheme. He showers, has breakfast, and reads the news — stock market updates are crucial in banking.\n\n**8:00 AM — Office Preparation**\n\nArjun commutes by his own car to the branch. The office opens at 10 AM, but he arrives by 8:30 to review overnight reports. In banking, every day brings new transactions, client issues, and regulatory requirements.\n\n**9:00 AM — Review of Overnight Activity**\n\nThe previous day's cash position, international transactions, and customer complaints are laid out. Arjun's team presents:\n- Deposit balance: ₹400 crores\n- Loan portfolio: ₹250 crores\n- Failed transactions that need investigation\n- VIP customer complaints\n\n**9:30 AM — Team Briefing**\n\nThe branch has 25 employees: tellers, relationship managers, accountants. Arjun briefs them on:\n- New loan products to sell\n- Customer targets for the month\n- Process improvements\n- Incentives for meeting targets\n\nIn banking, performance matters. The branch that meets targets gets incentives, promotions, and better postings.\n\n**10:00 AM — Branch Opening**\n\nThe branch opens. Within minutes, customers stream in:\n- Retirees withdrawing pensions\n- Business owners depositing daily collections\n- Job seekers opening salary accounts\n- Students applying for education loans\n\nArjun is visible, greeting customers, ensuring smooth operations.\n\n**11:00 AM — Loan Approvals**\n\nThis is where real power lies. Arjun sits with the Credit Officer to review loan applications:\n- Personal loan for ₹10 lakhs (approved in 5 minutes)\n- Home loan for ₹50 lakhs (needs CIBIL check, property evaluation)\n- Business loan for ₹25 lakhs (needs income proof, business verification)\n\nArjun can approve up to ₹75 lakhs independently. Above that, it goes to regional approval. The authority is delegated based on experience.\n\n**12:30 PM — Lunch**\n\nUsually at a nearby restaurant or sometimes the office pantry. The salary is good enough to eat well. With perks and incentives, an SBI PO can earn ₹50,000-70,000 monthly.\n\n**1:30 PM — Customer Interaction**\n\nA VIP customer — a business owner with ₹5 crore in deposits — walks in. Arjun personally attends to them. Building relationships is crucial. A single big customer can contribute significantly to branch performance.\n\n**2:00 PM — Compliance and Reporting**\n\nBanking is heavily regulated. RBI has rules for everything:\n- Capital adequacy ratios\n- NPA (Non-Performing Assets) management\n- KYC compliance\n- Anti-money laundering checks\n\nArjun spends time ensuring the branch meets all regulatory requirements. Non-compliance means penalties and reputation damage.\n\n**3:00 PM — Marketing and Sales**\n\nBanking is also a competitive business. Arjun plans strategies to:\n- Increase deposits (lower cost of funds)\n- Increase loans (higher revenue)\n- Cross-sell insurance and mutual funds\n- Retain existing customers\n\nHis performance metrics are tracked daily. Meeting targets directly impacts bonuses.\n\n**4:00 PM — Problem Solving**\n\nA customer's check bounced. An ATM ran out of cash. A visa application requires a bank letter. Arjun's phone doesn't stop ringing. As the manager, he's the final authority for exceptions and solutions.\n\n**5:00 PM — Cash Reconciliation**\n\nBefore closing, the cash desk must tally. This is critical — even a ₹10 discrepancy triggers an investigation. The accountants reconcile:\n- Physical cash count\n- Digital records\n- Deposit amounts\n- Withdrawal amounts\n\n**5:30 PM — End of Day Report**\n\nA comprehensive report goes to regional headquarters:\n- Daily deposits\n- Disbursements\n- ATM status\n- Any incidents\n- Customer complaints\n\n**6:00 PM — Branch Closure**\n\nThe branch closes. But Arjun stays back, working on emails, reports, and planning for tomorrow. Banking is demanding.\n\n**The SBI PO Perks**\n\n- **Housing**: Loan at 1% interest (vs. 6-8% market rate)\n- **Medical**: Comprehensive medical coverage for family\n- **Leave**: 45 days per year (much higher than private sector)\n- **Pension**: Secure pension after 20 years\n- **LFC (Leave Fare Concession)**: Subsidized travel for vacations\n- **Job Security**: Virtually impossible to get fired\n- **Gratuity**: Significant payout after retirement\n- **Bonuses**: Performance-linked incentives up to ₹2-3 lakhs yearly\n\n**Salary Breakdown**\n\n- Base Pay: ₹36,000\n- Dearness Allowance (50%): ₹18,000\n- HRA (20% for non-metro): ₹7,200\n- Transport Allowance: ₹1,800\n- Gross: ₹63,000\n- In-hand after deductions: ₹45,000-50,000\n- With incentives and bonuses: ₹60,000-75,000\n\n**The Career Path**\n\nYear 1-3: Probationary Officer (learning phase)\nYear 4-7: Officer (increased responsibilities)\nYear 7-15: Senior Officer / Specialist\nYear 15+: Manager / Regional Manager\nYear 25+: General Manager / Executive\n\nMany POs retire as GMs earning ₹1.5L+ monthly, with lifetime pension.\n\n**The Challenges**\n\n- **Target Pressure**: Meeting monthly/quarterly targets is stressful\n- **Regulatory Scrutiny**: RBI audits are frequent and intense\n- **Customer Issues**: Complaints from thousands of customers\n- **Work-Life Balance**: Banking hours can be demanding\n- **NPA Worries**: Managing non-performing assets is emotionally draining\n\n**Why SBI PO?**\n\nIf you want stability, decent salary, and respect, the SBI PO is excellent. You're not getting ultra-rich, but you're building a secure life. The job involves numbers, people, and decision-making.\n\nAfter 20 years, you can retire with a comfortable pension and live a middle-class life without financial stress. In a country with limited social security, that's valuable."
    },
    {
      "slug": "income-tax-inspector",
      "title": "A Day in the Life of an Income Tax Inspector — Raids, Returns & Revenue",
      "description": "Experience the thrilling (and demanding) life of an Income Tax Inspector who audits businesses, conducts raids, and ensures tax compliance.",
      "category": "SSC",
      "icon": "📊",
      "readTime": "12 min read",
      "content": "Today is different. Income Tax Inspector Priya gets a message at 7 AM: \"Report to regional office immediately. Operation at 9 AM.\"\n\nAn \"operation\" is a raid. And raids are the most exciting part of an IT inspector's job.\n\n**7:00 AM — The Alert**\n\nIncome Tax raids are planned with military precision. Priya is part of a 12-member team that will conduct a search and seizure operation at the premises of a business suspected of tax evasion.\n\nToday's target: A manufacturing company with suspected annual revenue of ₹50+ crores but reported taxes worth only ₹2 lakhs. The discrepancy: ₹48 crores of concealed income.\n\n**8:30 AM — Pre-Raid Briefing**\n\nThe team gathers at the regional office. The Deputy Commissioner briefs them:\n- Location: Industrial estate in Bangalore\n- Suspected violation: Cash payments, underreporting of revenue\n- Assets seized in similar cases: Gold worth ₹50 lakhs, vehicles, jewelry\n- Stay alert: You might find hidden compartments, aggressive businessmen\n\nThree officers are assigned to each section of the office. Police backup is on standby.\n\n**9:00 AM — The Raid Begins**\n\nPriya's team arrives in unmarked cars. They show the warrant to the guard. The manager panics — he knows what's coming.\n\n\"We're conducting a search operation under IT Act. No one is allowed to leave or make calls,\" announces the leading officer.\n\nThe raid is underway.\n\n**9:15 AM — Searching the Office**\n\nPriya heads to the accounts department. She's looking for:\n- Ledgers showing real transactions\n- Hidden cash\n- Offshore account details\n- Communication with shell companies\n- Undisclosed jewelry, vehicles\n\nWithin 20 minutes, they find a locker in the back office. It contains:\n- ₹45 lakhs in cash\n- Gold ornaments worth ₹20+ lakhs\n- Documents with coded references\n\nEverything is documented, photographed, and sealed.\n\n**11:00 AM — Interview with Management**\n\nThe owner is panicking. Priya asks questions:\n- \"What's this cash doing in the locker?\"\n- \"These payments to shell companies — what are they for?\"\n- \"Your reported income is ₹2 crores. Your bank deposits are ₹50 crores. Explain.\"\n\nThe owner stammers. He knows he's caught.\n\n**12:30 PM — Continuing the Raid**\n\nThe IT team doesn't stop for lunch during raids. They continue searching through files, computers, and hidden spaces. Sometimes, they find:\n- Concealed investments in real estate\n- Bribery arrangements with officials\n- Money laundering through shell companies\n- Unaccounted gold and jewelry\n\n**2:00 PM — Sealing Documents**\n\nAll suspicious documents are seized. They're photographed, listed, and sealed. The business owner is given a copy.\n\n\"You have the right to reply within 30 days,\" the officer announces.\n\nBut everyone knows that ₹45 lakhs in undisclosed cash is hard to explain.\n\n**4:00 PM — Raid Ends**\n\nAfter 7 hours, the raid concludes. Seized items are inventoried:\n- Cash: ₹45 lakhs\n- Gold: ₹22 lakhs\n- Documents (500+ pages)\n- Hard drives\n\nThese items are stored in a government vault.\n\n**5:00 PM — Case Filing**\n\nBack at the office, Priya begins documentation. She prepares:\n- Raid report\n- Inventory of seized items\n- Initial analysis\n- Preliminary findings\n\nThis will become evidence in court proceedings.\n\n**What's a Normal Day Like?**\n\nNot every day is a raid. Many days, Priya sits at her desk:\n\n**Regular Day — 9:30 AM to 5:30 PM**\n\n**Morning**: Processing income tax returns from individuals and businesses. She has a workload of 200+ files monthly. Each file requires:\n- Verification of income claims\n- Cross-checking with bank statements\n- Matching with employer records\n- Identifying red flags\n\n**Mid-Morning**: Interviewing taxpayers who have discrepancies.\n- \"Your reported income is ₹10 lakhs, but you bought a ₹50 lakh car. Where did the money come from?\"\n- \"Your spouse claimed exemptions for agriculture income, but your documents show it's leased property. That's not exempt.\"\n\n**Afternoon**: Assessment reports. Priya calculates the actual income and tax due:\n- If discrepancy is small: Issue revised assessment with penalty\n- If discrepancy is large: Refer to prosecution wing for possible criminal proceedings\n\n**Late Afternoon**: Correspondence with taxpayers, bank verifications, property checks.\n\n**The Powers of an IT Inspector**\n\nUnder the IT Act, an inspector can:\n- Search and seize property suspected to be involved in tax evasion\n- Summon any person to give evidence\n- Demand production of books of accounts\n- Interrogate suspects\n- Seizure of valuables without warrant in certain cases\n- Initiate prosecution against willful tax evaders\n\nThese are powerful tools. They're also why IT inspectors are both feared and respected.\n\n**The Salary & Perks**\n\n- Base Pay (Level 7): ₹44,900\n- Dearness Allowance: ₹22,450\n- HRA (20-30%): ₹13,470-13,470\n- Gross: ₹80,820\n- In-hand (after tax): ₹55,000-60,000\n\n- **Medical**: Free government hospital access\n- **Housing Loan**: ₹50 lakhs at 4% interest\n- **Vacation Travel**: 3-4 vacations annually with paid leave\n- **Pension**: Secure pension after 20 years\n- **Gratuity**: ₹25+ lakhs on retirement\n\n**Career Growth**\n\n- Level 7 (Inspector): ₹45K-60K\n- Level 8 (Senior Inspector): ₹60K-80K\n- Level 9 (Superintendent): ₹80K-120K\n- Level 10 (DG/Principal): ₹120K+\n\n**The Challenges**\n\n- **Risk**: Raids can be confrontational. Businessmen sometimes resist. Security threats are real.\n- **Pressure**: Political pressure from powerful businessmen\n- **Emotional Toll**: You're essentially punishing people, even if legally justified\n- **Hours**: Raids don't follow 9-5 schedules\n- **Documentation**: Endless paperwork and court appearances\n\n**Why Be an IT Inspector?**\n\nIf you enjoy investigation, problem-solving, and making a real difference (stopping tax evasion protects national revenue), this is ideal. The thrill of uncovering hidden wealth is addictive for some.\n\nYou're not getting rich, but you're getting power, stability, and the satisfaction of serving justice."
    },
    {
      "slug": "railway-station-master",
      "title": "A Day in the Life of a Railway Station Master",
      "description": "Manage 300+ trains daily, ensure passenger safety, and lead a team at one of India's busiest railway stations.",
      "category": "Railway",
      "icon": "🚂",
      "readTime": "10 min read",
      "content": "At 3:45 AM, Vikram's alarm goes off. He's the Station Master at Mumbai Central Railway Station, one of India's busiest terminals. Today, 312 trains will pass through his station. 500,000 passengers. His responsibility: Safety, punctuality, and order.\n\n**4:00 AM — Before the Rush**\n\nVikram arrives at the station by 5 AM. The evening shift staff briefs him on:\n- Any incidents overnight\n- Breakdown of any trains\n- Last-minute schedule changes\n- VIP passengers traveling\n\nAll overnight reports are documented. A single accident is a disaster — not just for passengers, but for his career.\n\n**5:30 AM — Pre-Shift Briefing**\n\nThe Station Master chairs a meeting with:\n- Platform staff (5-10 per platform)\n- Ticket collectors\n- Security personnel\n- Maintenance crew\n- Signaling staff\n\nToday's focus:\n- Platform 1: A special train carrying an important minister. Extra security and protocol required.\n- Platform 3: A train is 45 minutes behind schedule. Passengers are angry.\n- Maintenance: Overhead wire damaged near Platform 5. Limited traffic possible.\n\n**6:00 AM — The Trains Start**\n\nThe first train departs at 6:15 AM. Vikram watches from the control room:\n- Green light from signaling: All clear\n- Train leaves on time\n- Platform is cleared\n\nThis happens 312 times today.\n\n**7:00 AM — Peak Hours Begin**\n\nBy 7 AM, thousands of commuters flood the station. Platforms are packed. The ticket counters have 50+ people waiting.\n\nVikram monitors:\n- No overcrowding on platforms\n- Disabled passengers assisted\n- Lost children reunited with parents\n- Arguments between passengers resolved\n- Pickpockets apprehended by security\n\n**9:00 AM — Administrative Work**\n\nVikram's office is adjacent to the main control room. He processes:\n- Station performance reports\n- Passenger complaints\n- Staff leave applications\n- Maintenance requests\n- Budget approvals for station upkeep\n\n**10:00 AM — The Minister's Train**\n\nA special train carrying a national minister arrives. Vikram personally supervises:\n- Platforms cleared of other passengers\n- Red carpet rolled out\n- Security screened\n- VIP receiving team ready\n\nThe minister arrives, shakes Vikram's hand, and departs. It's a 2-minute interaction, but it matters for performance records.\n\n**11:00 AM — Handling Delays**\n\nA train from Delhi is delayed by 2 hours due to a track accident. Thousands of passengers are stuck. Vikram must:\n- Announce the delay\n- Provide refreshment to passengers\n- Arrange alternative transport where needed\n- Liaise with railway authorities\n- Keep passengers calm\n\n**12:30 PM — Lunch Break**\n\nVikram eats at the officer's mess. The meal is heavily subsidized — a full vegetarian or non-vegetarian meal costs only ₹20-30.\n\n**1:30 PM — Afternoon Operations**\n\nThe afternoon brings lighter traffic, but operations continue smoothly:\n- Train arrivals and departures\n- Passenger inquiries\n- Lost and found items\n- Staff coordination\n\n**3:00 PM — Inspections**\n\nVikram walks the platforms:\n- Check cleanliness\n- Check signage\n- Ensure disabled facilities are operational\n- Speak with staff\n\nStation hygiene and passenger experience directly affect ratings.\n\n**4:30 PM — Evening Peak**\n\nThe second rush hour begins. Again, thousands of passengers. Vikram is back to monitoring crowding, safety, and punctuality.\n\n**6:00 PM — Handover Meeting**\n\nThe evening shift Station Master arrives. Vikram briefs them on:\n- Any ongoing issues\n- Special trains in evening\n- Maintenance work scheduled\n- Staff absences\n- Performance metrics for the day\n\n**6:30 PM — End of Shift**\n\nVikram departs. His day is done, but his accountability isn't. A single accident tomorrow will be traced back to his watch.\n\n**The Real Power of a Station Master**\n\n- **Authority**: Can order trains to stop, change platforms, or divert\n- **Safety**: Has final authority on passenger safety\n- **Discipline**: Can suspend or transfer staff\n- **Budget**: Can approve expenditure for station maintenance up to ₹5 lakhs\n- **Protocol**: Sets rules for the station\n\n**The Legendary Perk: Free Lifetime Rail Travel**\n\nThis is the perk every railway employee dreams of:\n- **Unlimited rail travel** for the officer and immediate family (spouse + children)\n- **Lifetime validity** — even after retirement\n- **First or Second Class** — depending on grade\n- **Free for family** — passes extend to dependents\n- **Annual expenses saved**: ₹50,000+ for a family using trains regularly\n\nSome officers' families travel continuously — visiting relatives, vacations, exploring India — all for free.\n\n**Housing and Other Perks**\n\n- **Railway Quarters**: Subsidized housing near the station\n- **LTC (Leave Travel Concession)**: Biennial paid travel to any part of India\n- **Medical**: Free treatment at railway hospitals\n- **Pension**: Secure pension after 20 years\n- **CSD Canteen**: Access to discounted goods (groceries, appliances)\n\n**Salary Structure**\n\n- Base Pay (Level 5): ₹19,900\n- Dearness Allowance: ₹9,950\n- HRA: ₹3,980\n- Transport Allowance: ₹1,800\n- Gross: ₹35,630\n- In-hand: ₹25,000-28,000\n\n**The Challenge of Being a Station Master**\n\nOne accident — one derailment, one overcrowding incident — can destroy your career. The responsibility is immense. You're managing the lives of half a million passengers annually.\n\nBut if you love order, systems, and ensuring safety for thousands daily, the railway service is calling.\n\nAnd the free lifetime rail travel? That's a gift that keeps giving for 40+ years."
    },
    {
      "slug": "rbi-grade-b",
      "title": "A Day in the Life of an RBI Grade B Officer",
      "description": "Experience the prestigious world of RBI Grade B — central banking, monetary policy, and shaping India's financial system.",
      "category": "Banking",
      "icon": "🏛️",
      "readTime": "11 min read",
      "content": "Ananya walks into the Reserve Bank of India's main campus in Mumbai at 9:00 AM. The campus is sprawling, green, and exudes authority. She's an RBI Grade B officer, one of India's most prestigious positions. Her job? To help shape India's monetary policy and banking system.\n\n**9:30 AM — Morning Meeting**\n\nAnanya's department deals with \"Banking Regulation & Supervision.\" Her team of 15 officers works on:\n- New banking licenses\n- Compliance monitoring\n- Lending standards\n- Consumer protection\n\nToday, the focus is on a new fintech company applying for a banking license. Ananya's team must evaluate:\n- Regulatory capital\n- Technology infrastructure\n- Risk management\n- Compliance capability\n\nOne decision affects lakhs of customers and billions of rupees.\n\n**10:30 AM — Analysis & Research**\n\nAnanya sits at her desk, reviewing:\n- Banking sector trends\n- NPL (Non-Performing Loan) ratios across banks\n- Inflation data\n- Monetary policy implications\n\nHer insights will feed into RBI's policy recommendations.\n\n**11:30 AM — Committee Meeting**\n\nA committee discusses regulatory changes:\n- Should loan limits be raised for priority sector lending?\n- How should shadow banking be regulated?\n- What are the implications of digital payments on traditional banking?\n\nAnanya contributes expertise. Her point of view might be included in RBI's next policy circular.\n\n**1:00 PM — Lunch**\n\nThe RBI's officer's cafeteria serves excellent meals at subsidized rates. Ananya eats with colleagues, discussing both work and non-work topics. Networking is subtle but important.\n\n**2:00 PM — External Liaison**\n\nAnanya takes a call from a bank's CEO. A new regulation affects their business model. The CEO is seeking clarification. Ananya explains RBI's intent and helps them develop a compliance strategy.\n\nThis relationship-building is crucial. RBI works closely with the banking industry.\n\n**3:00 PM — Inspection Report Review**\n\nAn RBI team conducted a bank inspection last month. The report is concerning:\n- The bank has high NPA rates\n- Risk management systems are weak\n- Lending practices are risky\n\nAnanya prepares a response:\n- RBI will issue a \"Supervisory Letter\" with mandatory actions\n- The bank must remediate within 90 days\n- Failure means regulatory consequences\n\n**4:00 PM — Policy Research**\n\nAnanya drafts a brief on \"Impact of AI in Banking.\" RBI wants to understand how artificial intelligence will change:\n- Lending decisions\n- Fraud detection\n- Customer service\n- Systemic risks\n\nHer research will inform RBI's upcoming framework for AI in finance.\n\n**5:00 PM — Governor's Office**\n\nAnanya's boss (the Deputy Governor) is briefing the RBI Governor on current issues. Ananya joins to provide technical input.\n\nThe Governor is thinking about next month's monetary policy decision:\n- Should interest rates be raised or lowered?\n- What's the inflation forecast?\n- What are global factors?\n\nAnanya presents analysis. The Governor listens, asks sharp questions, and makes notes.\n\nThis is the power of Grade B at RBI: Your analysis directly influences India's economic policy.\n\n**5:30 PM — Email Review**\n\nAnanya responds to dozens of emails:\n- A bank's query on regulatory interpretation\n- A consumer complaint about a bank\n- Internal RBI memos\n- Coordination with international organizations (IMF, World Bank)\n\n**6:30 PM — Departure**\n\nAnanya leaves the office, but her work continues mentally. Central banking is never completely off your mind.\n\n**What Makes RBI Grade B Special?**\n\n**Prestige**: The RBI is India's central bank. Working here is the pinnacle of financial careers. Officers are referred to as \"the most intelligent bureaucrats.\"\n\n**Influence**: Your recommendations shape policy affecting 1.4 billion people.\n\n**Salary**: Starting from day 1, ₹1,00,000+ monthly is common.\n\n**Exposure**: International visits, meetings with World Bank officials, papers presented at global forums.\n\n**The Salary Structure**\n\n- Base Pay (Grade B): ₹55,220\n- Dearness Allowance: ₹27,610\n- HRA (30% for metro): ₹16,566\n- Transport Allowance: ₹3,600\n- Gross: ₹1,03,596\n- In-hand (after tax): ₹70,000-75,000\n\n**Career Progression**\n\n- Grade B (Year 1-5): ₹70K-80K in-hand\n- Grade A (Year 6-15): ₹1,00K-130K in-hand\n- Senior Management (Year 15+): ₹1,50K-200K in-hand\n\n**Perks & Benefits**\n\n- **Housing Loan**: ₹70 lakhs at 0.5% interest (nearly free money)\n- **Medical**: World-class medical coverage\n- **Pension**: RBI pension is among India's best\n- **LTC**: Biennial fully paid travel\n- **Sabbatical**: Can take sabbatical for studies (e.g., PhD) while on payroll\n- **International Postings**: Opportunities to work at RBI's overseas centers or with international organizations\n- **Gratuity**: ₹50+ lakhs on retirement\n\n**The Work Culture**\n\nRBI attracts the best minds in finance:\n- Officers have MBAs from IIM, XLRI, ISB\n- Economists with PhDs from global universities\n- Some are published researchers\n\nThe environment is intellectually stimulating. You're solving real problems that affect the economy.\n\n**The Challenges**\n\n- **Pressure**: Your decisions affect millions of people and trillions in assets\n- **Complexity**: Banking, finance, and economics are complex fields\n- **Political Interference**: Sometimes, governments push for policies RBI disagrees with\n- **Long Hours**: During crisis (like the 2008 financial crisis), 12-hour days are common\n- **Limited Transparency**: Some decisions are confidential, limiting public credit\n\n**Why RBI Grade B?**\n\nIf you love economics, policy-making, and influencing the nation's financial system, this is the ultimate job. The salary is great, but the real reward is knowing your work impacts millions.\n\nYou're not managing a bank's profits. You're ensuring India's banking system remains stable and fair. That's a profound responsibility — and calling."
    },
    {
      "slug": "nda-army-officer",
      "title": "A Day in the Life of an Indian Army Officer — NDA to First Posting",
      "description": "From IMA Dehradun to your first posting — the thrilling, challenging life of an Indian Army officer.",
      "category": "Defence",
      "icon": "⚔️",
      "readTime": "11 min read",
      "content": "Lieutenant Aditya wakes up at 5:00 AM to the sound of reveille bugle. He's at his first posting — a military station near the Indo-China border. Two years have passed since he graduated from IMA Dehradun, and every day still feels surreal.\n\n**5:00 AM — Reveille & PT (Physical Training)**\n\nIn the army, the day starts before sunrise. Aditya steps out in PT uniform — shorts and a T-shirt — and jogs with his platoon. 40 soldiers run in formation, chanting motivational phrases.\n\nPhysical fitness isn't optional. It's a measure of discipline and capability.\n\n**6:00 AM — Breakfast**\n\nThe soldiers march to the mess. The meal is simple but nutritious:\n- Chapati (Indian bread)\n- Curry\n- Dal (lentil)\n- Rice\n- Milk\n- Fruit\n\nAditya eats with his soldiers. In the army, officers eat the same food as troops. This builds trust.\n\n**6:45 AM — Parade & Briefing**\n\nAll officers and soldiers gather for morning briefing. The Commanding Officer (Colonel) briefs:\n- Deployment near the border\n- Security concerns\n- Training exercises\n- Discipline issues\n\nToday, Aditya's platoon (40 soldiers) will conduct a patrol near the border. It's a routine patrol, but every patrol carries risks.\n\n**7:30 AM — Preparation**\n\nAditya briefed his soldiers:\n- Route for today's patrol\n- Security procedures\n- Emergency protocol\n- Positions in case of enemy contact\n\nSoldiers check weapons, ammunition, communication devices, and medical kits.\n\n**8:00 AM — Patrol Begins**\n\nAditya leads 40 soldiers on a 15 km patrol. They're looking for:\n- Infiltrators from across the border\n- Suspicious activities\n- Maintenance of boundary markers\n- Presence verification (India must show active presence)\n\nEvery soldier is alert. Every tree and rock could hide an enemy. This isn't training. This is real.\n\n**10:30 AM — Border Reality**\n\nThe soldiers reach the border. On one side: India. On the other side: The neighboring country. The Line of Control (LOC) is just a few hundred meters away.\n\nAditya feels the weight of responsibility. He's responsible for the lives of 40 soldiers. A single mistake — stepping across the border — could spark an international incident.\n\n**12:00 PM — Return to Base**\n\nThe patrol returns safely. No incidents. But the vigilance never stops.\n\n**1:00 PM — Lunch**\n\nBack at the mess, lunch is served. The food is better than patrol rations:\n- Mutton curry\n- Vegetables\n- Bread\n- Tea\n\n**2:00 PM — Administrative Work**\n\nAditya's day shifts from operations to administration:\n- Soldier performance reviews\n- Leave applications\n- Training schedules\n- Maintenance reports\n- Correspondence with higher command\n\n**3:00 PM — Officer's Mess**\n\nAditya joins other junior officers at the officer's mess. They discuss:\n- Career prospects\n- Postings\n- Training courses\n- Marriages\n- Future plans\n\nThe camaraderie is special. These are people you might fight alongside, die with, or save.\n\n**4:00 PM — Training**\n\nJunior officers receive weekly training:\n- Leadership techniques\n- Tactical decision-making\n- Communication skills\n- Foreign languages\n\nToday's session is on \"Crisis Management.\" An officer from HQ teaches how to handle unexpected situations.\n\n**5:30 PM — Dinner Preparation**\n\nAditya checks on his soldiers' mess:\n- Is food adequate?\n- Is hygiene maintained?\n- Are soldiers satisfied?\n\nLeadership means caring for your people's basic needs.\n\n**6:30 PM — Evening Briefing**\n\nThe platoon gathers for evening briefing:\n- Tomorrow's plans\n- Any changes in protocol\n- Welfare updates\n\n**7:30 PM — Dinner**\n\nAditya dines with his soldiers again. Eating together builds unit cohesion.\n\n**8:30 PM — Rest & Reflection**\n\nAditya returns to his quarters — a modest bungalow within the base. He writes letters, reads, or watches cricket on a small TV.\n\nInternet connectivity is limited at forward bases. Communication with family is sporadic.\n\n**The Life at IMA (Indian Military Academy)**\n\nBefore this first posting, Aditya spent 1 year at IMA in Dehradun. The training was intense:\n\n- **Academics**: Military science, strategy, leadership, history\n- **Physical Training**: Extreme fitness standards\n- **Drill & Discipline**: Hours of parade ground training\n- **Field Exercises**: Overnight camps, survival skills\n- **Leadership Challenges**: Making decisions under stress\n- **Horse Riding**: Centuries-old cavalry tradition\n- **Shooting**: Rifle and pistol marksmanship\n\nGraduation from IMA is an honor. Parents, generals, and dignitaries attend. Passing-out parade is a grandeur spectacle.\n\n**The Salary & Allowances**\n\n- Base Pay (Lieutenant, Level 10): ₹56,100\n- Dearness Allowance: ₹28,050\n- HRA (varies by station): ₹5,000-15,000\n- Field Area Allowance (forward posting): ₹8,000-12,000\n- Commuted Rations (food subsidy): ₹2,000\n- Other allowances: ₹3,000-5,000\n- Total Gross: ₹1,02,150-1,24,150\n- In-hand: ₹65,000-75,000\n\n**Perks of Military Service**\n\n- **Free Housing**: On-base accommodation provided\n- **Subsidized Food**: Officers mess provides meals at ₹500/month\n- **Free Medical**: Military hospital access for officer and family\n- **CSD Canteen**: Discounted goods (40-50% cheaper than markets)\n- **Leave**: 45 days per year + special leave for emergencies\n- **LTC**: Fully paid travel for family twice every 2 years\n- **Gratuity**: ₹30+ lakhs on retirement\n- **Pension**: Starting from ₹40,000+ monthly (for a Lieutenant)\n- **Respect**: In Indian society, uniformed officers are deeply respected\n\n**Career Progression**\n\n- Lieutenant (0-3 years): ₹60K-70K\n- Captain (3-8 years): ₹75K-90K\n- Major (8-15 years): ₹1,00K-1,30K\n- Lieutenant Colonel (15-20 years): ₹1,40K-1,70K\n- Colonel+ (20+ years): ₹1,80K+\n\n**The Unique Aspect: Camaraderie**\n\nThe bond between soldiers is unlike any other profession. You eat together, train together, face danger together. This creates a brotherhood that lasts a lifetime.\n\n**The Challenges**\n\n- **Danger**: Soldiers are killed or injured in operational duties\n- **Separation**: Years away from family in forward postings\n- **Stress**: Making life-and-death decisions\n- **Limited Freedom**: Army life is highly regulated\n- **Transferable Skills**: Some skills don't translate to civilian life\n\n**The Calling**\n\nArmy officers aren't motivated by salary alone. They're motivated by:\n- **Patriotism**: Serving the nation\n- **Honor**: Being part of India's finest\n- **Camaraderie**: Brotherhood with fellow officers\n- **Adventure**: Challenging postings, exciting deployments\n- **Purpose**: Protecting India's borders and citizens\n\nAditya's parents were skeptical initially. But now, watching their son lead soldiers with confidence and discipline, they're proud.\n\nThe army isn't just a job. It's a way of life. And for those called to serve, it's the greatest honor."
    }
  ]
}